pinit_pkg/__init__.py
pinit_pkg/errors.py
pinit_pkg/kms.py
pinit_pkg/request.py
pinit_pkg/responses.py
pinit_pkg/s3.py
pinit_pkg/schemas.py
pinit_pkg/types.py
pinit_pkg/utils.py
pinit_pkg/decorators/__init__.py
pinit_pkg/decorators/auth.py
pinit_pkg/decorators/execution_time.py
pinit_pkg/decorators/lambda_handler.py
pinit_pkg-0.1.39.dist-info/METADATA
pinit_pkg-0.1.39.dist-info/WHEEL
pinit_pkg-0.1.39.dist-info/top_level.txt
pinit_pkg-0.1.39.dist-info/RECORD
