Metadata-Version: 2.4
Name: pinit-pkg
Version: 0.1.39
Summary: Paquete de utilidades para el servicio de clusterizado.
Author: Eduardo Cifuentes
Author-email: eduardo.cifuentes@bigsmart.mx
Classifier: Programming Language :: Python :: 3
Classifier: Operating System :: OS Independent
Requires-Python: >=3.6
Requires-Dist: boto3
Requires-Dist: loguru
Requires-Dist: pydantic
Requires-Dist: python-dotenv
Requires-Dist: PyJWT
Requires-Dist: cryptography
Dynamic: author
Dynamic: author-email
Dynamic: classifier
Dynamic: description
Dynamic: description-content-type
Dynamic: requires-dist
Dynamic: requires-python
Dynamic: summary
